exhibit/__init__.py
exhibit/__main__.py
exhibit/command/__init__.py
exhibit/command/bootstrap.py
exhibit/command/tests/__init__.py
exhibit/command/tests/test_bootstrap.py
exhibit/command/tests/test_performance.py
exhibit/core/__init__.py
exhibit/core/constants.py
exhibit/core/constraints.py
exhibit/core/exhibit.py
exhibit/core/formatters.py
exhibit/core/spec.py
exhibit/core/sql.py
exhibit/core/utils.py
exhibit/core/validator.py
exhibit/core/generate/__init__.py
exhibit/core/generate/categorical.py
exhibit/core/generate/continuous.py
exhibit/core/generate/derived.py
exhibit/core/generate/geo.py
exhibit/core/generate/missing.py
exhibit/core/generate/regex.py
exhibit/core/generate/uuids.py
exhibit/core/generate/weights.py
exhibit/core/generate/yaml.py
exhibit/core/generate/tests/__init__.py
exhibit/core/generate/tests/test_categorical.py
exhibit/core/generate/tests/test_continuous.py
exhibit/core/generate/tests/test_derived.py
exhibit/core/generate/tests/test_geo.py
exhibit/core/generate/tests/test_missing.py
exhibit/core/generate/tests/test_regex.py
exhibit/core/generate/tests/test_uuid.py
exhibit/core/generate/tests/test_weights.py
exhibit/core/generate/tests/test_yaml.py
exhibit/core/linkage/__init__.py
exhibit/core/linkage/hierarchical.py
exhibit/core/linkage/matrix.py
exhibit/core/linkage/tests/__init__.py
exhibit/core/linkage/tests/test_linkage_hierarchical.py
exhibit/core/linkage/tests/test_linkage_matrix.py
exhibit/core/tests/__init__.py
exhibit/core/tests/test_constraints.py
exhibit/core/tests/test_exhibit.py
exhibit/core/tests/test_formatters.py
exhibit/core/tests/test_reference.py
exhibit/core/tests/test_spec.py
exhibit/core/tests/test_sql.py
exhibit/core/tests/test_utils.py
exhibit/core/tests/test_uuids.py
exhibit/core/tests/test_validator.py
exhibit/core/tests/_reference_data/inpatients_anon_mnt_il10.csv
exhibit/core/tests/_reference_data/inpatients_anon_mnt_il50.csv
exhibit/core/tests/_reference_data/inpatients_anon_rnd_il10.csv
exhibit-0.9.9.dist-info/LICENSE
exhibit-0.9.9.dist-info/METADATA
exhibit-0.9.9.dist-info/WHEEL
exhibit-0.9.9.dist-info/entry_points.txt
exhibit-0.9.9.dist-info/top_level.txt
exhibit-0.9.9.dist-info/RECORD
