Metadata-Version: 2.1
Name: exhibit
Version: 0.9.9
Summary: Command line tool to generate anonymised demonstrator data
Home-page: https://github.com/gherka/exhibit
Author: German Priks
Author-email: german.priks@pm.me
Classifier: Programming Language :: Python :: 3
Classifier: Programming Language :: Python :: 3.10
Classifier: Programming Language :: Python :: 3.11
Classifier: Programming Language :: Python :: 3.12
Classifier: License :: OSI Approved :: GNU Affero General Public License v3 or later (AGPLv3+)
Classifier: Operating System :: OS Independent
Classifier: Development Status :: 4 - Beta
Classifier: Intended Audience :: Healthcare Industry
Classifier: Intended Audience :: Science/Research
Classifier: Topic :: Scientific/Engineering :: Information Analysis
Classifier: Topic :: Security
Requires-Python: >=3.10
License-File: LICENSE
Requires-Dist: dill==0.3.8
Requires-Dist: h3==3.7.7
Requires-Dist: numpy==2.1.1
Requires-Dist: pandas==2.2.2
Requires-Dist: pyarrow==17.0.0
Requires-Dist: pyyaml==6.0.2
Requires-Dist: scipy==1.14.1
Requires-Dist: shapely==2.0.6
Requires-Dist: sql-metadata==2.13.0
Requires-Dist: sqlalchemy==2.0.34
Provides-Extra: dev
Requires-Dist: memory-profiler; extra == "dev"
